{
"autoplayBgm":false,"autoplayBgs":false,"battleback1Name":"","battleback2Name":"","bgm":{"name":"","pan":0,"pitch":100,"volume":90},"bgs":{"name":"","pan":0,"pitch":100,"volume":90},"disableDashing":true,"displayName":"","encounterList":[],"encounterStep":30,"height":13,"note":"","parallaxLoopX":false,"parallaxLoopY":false,"parallaxName":"","parallaxShow":true,"parallaxSx":0,"parallaxSy":0,"scrollType":0,"specifyBattleback":false,"tilesetId":1,"width":17,
"data":[0,0,0,0,0,0,0,0,0,0,0,0,0,0,0,0,0,0,0,0,0,0,0,0,0,0,0,0,0,0,0,0,0,0,0,0,0,0,0,0,0,0,0,0,0,0,0,0,0,0,0,0,0,0,0,0,0,0,0,0,0,0,0,0,0,0,0,0,0,0,0,0,0,0,0,0,0,0,0,0,0,0,0,0,0,0,0,0,0,0,0,0,0,0,0,0,0,0,0,0,0,0,0,0,0,0,0,0,0,0,0,0,0,0,0,0,0,0,0,0,0,0,0,0,0,0,0,0,0,0,0,0,0,0,0,0,0,0,0,0,0,0,0,0,0,0,0,0,0,0,0,0,0,0,0,0,0,0,0,0,0,0,0,0,0,0,0,0,0,0,0,0,0,0,0,0,0,0,0,0,0,0,0,0,0,0,0,0,0,0,0,0,0,0,0,0,0,0,0,0,0,0,0,0,0,0,0,0,0,0,0,0,0,0,0,0,0,0,0,0,0,0,0,0,0,0,0,0,0,0,0,0,0,0,0,0,0,0,0,0,0,0,0,0,0,0,0,0,0,0,0,0,0,0,0,0,0,0,0,0,0,0,0,0,0,0,0,0,0,0,0,0,0,0,0,0,0,0,0,0,0,0,0,0,0,0,0,0,0,0,0,0,0,0,0,0,0,0,0,0,0,0,0,0,0,0,0,0,0,0,0,0,0,0,0,0,0,0,0,0,0,0,0,0,0,0,0,0,0,0,0,0,0,0,0,0,0,0,0,0,0,0,0,0,0,0,0,0,0,0,0,0,0,0,0,0,0,0,0,0,0,0,0,0,0,0,0,0,0,0,0,0,0,0,0,0,0,0,0,0,0,0,0,0,0,0,0,0,0,0,0,0,0,0,0,0,0,0,0,0,0,0,0,0,0,0,0,0,0,0,0,0,0,0,0,0,0,0,0,0,0,0,0,0,0,0,0,0,0,0,0,0,0,0,0,0,0,0,0,0,0,0,0,0,0,0,0,0,0,0,0,0,0,0,0,0,0,0,0,0,0,0,0,0,0,0,0,0,0,0,0,0,0,0,0,0,0,0,0,0,0,0,0,0,0,0,0,0,0,0,0,0,0,0,0,0,0,0,0,0,0,0,0,0,0,0,0,0,0,0,0,0,0,0,0,0,0,0,0,0,0,0,0,0,0,0,0,0,0,0,0,0,0,0,0,0,0,0,0,0,0,0,0,0,0,0,0,0,0,0,0,0,0,0,0,0,0,0,0,0,0,0,0,0,0,0,0,0,0,0,0,0,0,0,0,0,0,0,0,0,0,0,0,0,0,0,0,0,0,0,0,0,0,0,0,0,0,0,0,0,0,0,0,0,0,0,0,0,0,0,0,0,0,0,0,0,0,0,0,0,0,0,0,0,0,0,0,0,0,0,0,0,0,0,0,0,0,0,0,0,0,0,0,0,0,0,0,0,0,0,0,0,0,0,0,0,0,0,0,0,0,0,0,0,0,0,0,0,0,0,0,0,0,0,0,0,0,0,0,0,0,0,0,0,0,0,0,0,0,0,0,0,0,0,0,0,0,0,0,0,0,0,0,0,0,0,0,0,0,0,0,0,0,0,0,0,0,0,0,0,0,0,0,0,0,0,0,0,0,0,0,0,0,0,0,0,0,0,0,0,0,0,0,0,0,0,0,0,0,0,0,0,0,0,0,0,0,0,0,0,0,0,0,0,0,0,0,0,0,0,0,0,0,0,0,0,0,0,0,0,0,0,0,0,0,0,0,0,0,0,0,0,0,0,0,0,0,0,0,0,0,0,0,0,0,0,0,0,0,0,0,0,0,0,0,0,0,0,0,0,0,0,0,0,0,0,0,0,0,0,0,0,0,0,0,0,0,0,0,0,0,0,0,0,0,0,0,0,0,0,0,0,0,0,0,0,0,0,0,0,0,0,0,0,0,0,0,0,0,0,0,0,0,0,0,0,0,0,0,0,0,0,0,0,0,0,0,0,0,0,0,0,0,0,0,0,0,0,0,0,0,0,0,0,0,0,0,0,0,0,0,0,0,0,0,0,0,0,0,0,0,0,0,0,0,0,0,0,0,0,0,0,0,0,0,0,0,0,0,0,0,0,0,0,0,0,0,0,0,0,0,0,0,0,0,0,0,0,0,0,0,0,0,0,0,0,0,0,0,0,0,0,0,0,0,0,0,0,0,0,0,0,0,0,0,0,0,0,0,0,0,0,0,0,0,0,0,0,0,0,0,0,0,0,0,0,0,0,0,0,0,0,0,0,0,0,0,0,0,0,0,0,0,0,0,0,0,0,0,0,0,0,0,0,0,0,0,0,0,0,0,0,0,0,0,0,0,0,0,0,0,0,0,0,0,0,0,0,0,0,0,0,0,0,0,0,0,0,0,0,0,0,0,0,0,0,0,0,0,0,0,0,0,0,0,0,0,0,0,0,0,0,0,0,0,0,0,0,0,0,0,0,0,0,0,0,0,0,0,0,0,0,0,0,0,0,0,0,0,0,0,0,0,0,0,0,0,0,0,0,0,0,0,0,0,0,0,0,0,0,0,0,0,0,0,0,0,0,0,0,0,0,0,0,0,0,0,0,0,0,0,0,0,0,0,0,0,0,0,0,0,0,0,0,0,0,0,0,0,0,0,0,0,0,0,0,0,0,0,0,0,0,0,0,0,0,0,0,0,0,0,0,0,0,0,0,0,0,0,0,0,0,0,0,0,0,0,0,0,0,0,0,0,0,0,0,0,0,0,0,0,0,0,0,0,0,0,0,0,0,0,0,0,0,0,0,0,0,0,0,0,0,0,0,0,0,0,0,0,0,0,0,0,0,0,0,0,0,0,0,0,0,0,0,0,0,0,0,0,0,0,0,0,0,0,0,0,0,0,0,0,0,0,0,0,0,0,0,0,0,0,0,0,0,0,0,0,0,0,0,0,0,0,0,0,0,0,0,0,0,0,0,0,0,0,0],
"events":[
null,
{"id":1,"name":"主角1 換手用","note":"","pages":[{"conditions":{"actorId":2,"actorValid":true,"itemId":1,"itemValid":false,"selfSwitchCh":"A","selfSwitchValid":false,"switch1Id":165,"switch1Valid":true,"switch2Id":166,"switch2Valid":true,"variableId":105,"variableValid":false,"variableValue":1},"directionFix":false,"image":{"tileId":0,"characterName":"$actor1","direction":2,"pattern":1,"characterIndex":0},"moveFrequency":3,"moveRoute":{"list":[{"code":0,"indent":null,"parameters":[]}],"repeat":true,"skippable":false,"wait":false},"moveSpeed":3,"moveType":0,"priorityType":1,"stepAnime":false,"through":false,"trigger":0,"walkAnime":true,"list":[{"code":117,"indent":0,"parameters":[95]},{"code":0,"indent":0,"parameters":[]}]},{"conditions":{"actorId":1,"actorValid":true,"itemId":1,"itemValid":false,"selfSwitchCh":"A","selfSwitchValid":false,"switch1Id":1,"switch1Valid":false,"switch2Id":1,"switch2Valid":false,"variableId":1,"variableValid":false,"variableValue":0},"directionFix":false,"image":{"characterIndex":0,"characterName":"","direction":2,"pattern":0,"tileId":0},"list":[{"code":0,"indent":0,"parameters":[]}],"moveFrequency":3,"moveRoute":{"list":[{"code":0,"parameters":[]}],"repeat":true,"skippable":false,"wait":false},"moveSpeed":3,"moveType":0,"priorityType":0,"stepAnime":false,"through":false,"trigger":0,"walkAnime":true}],"x":0,"y":0},
{"id":2,"name":"主角2 換手用","note":"","pages":[{"conditions":{"actorId":1,"actorValid":true,"itemId":1,"itemValid":false,"selfSwitchCh":"A","selfSwitchValid":false,"switch1Id":165,"switch1Valid":true,"switch2Id":166,"switch2Valid":true,"variableId":234,"variableValid":false,"variableValue":1},"directionFix":false,"image":{"tileId":0,"characterName":"$actor2","direction":2,"pattern":1,"characterIndex":0},"moveFrequency":3,"moveRoute":{"list":[{"code":0,"indent":null,"parameters":[]}],"repeat":true,"skippable":false,"wait":false},"moveSpeed":3,"moveType":0,"priorityType":1,"stepAnime":false,"through":false,"trigger":0,"walkAnime":true,"list":[{"code":117,"indent":0,"parameters":[96]},{"code":0,"indent":0,"parameters":[]}]},{"conditions":{"actorId":2,"actorValid":true,"itemId":1,"itemValid":false,"selfSwitchCh":"A","selfSwitchValid":false,"switch1Id":1,"switch1Valid":false,"switch2Id":1,"switch2Valid":false,"variableId":1,"variableValid":false,"variableValue":0},"directionFix":false,"image":{"characterIndex":0,"characterName":"","direction":2,"pattern":0,"tileId":0},"list":[{"code":0,"indent":0,"parameters":[]}],"moveFrequency":3,"moveRoute":{"list":[{"code":0,"parameters":[]}],"repeat":true,"skippable":false,"wait":false},"moveSpeed":3,"moveType":0,"priorityType":0,"stepAnime":false,"through":false,"trigger":0,"walkAnime":true}],"x":1,"y":0},
null,
{"id":4,"name":"EV004","note":"","pages":[{"conditions":{"actorId":1,"actorValid":false,"itemId":1,"itemValid":false,"selfSwitchCh":"A","selfSwitchValid":false,"switch1Id":1,"switch1Valid":false,"switch2Id":1,"switch2Valid":false,"variableId":1,"variableValid":false,"variableValue":0},"directionFix":false,"image":{"characterIndex":0,"characterName":"","direction":2,"pattern":0,"tileId":0},"list":[{"code":231,"indent":0,"parameters":[41,"Dark_B",0,0,0,0,100,100,0,0]},{"code":117,"indent":0,"parameters":[1]},{"code":221,"indent":0,"parameters":[]},{"code":201,"indent":0,"parameters":[0,6,26,7,2,2]},{"code":211,"indent":0,"parameters":[1]},{"code":117,"indent":0,"parameters":[18]},{"code":0,"indent":0,"parameters":[]}],"moveFrequency":3,"moveRoute":{"list":[{"code":0,"parameters":[]}],"repeat":true,"skippable":false,"wait":false},"moveSpeed":3,"moveType":0,"priorityType":0,"stepAnime":false,"through":false,"trigger":3,"walkAnime":true},{"conditions":{"actorId":1,"actorValid":false,"itemId":1,"itemValid":false,"selfSwitchCh":"A","selfSwitchValid":false,"switch1Id":1,"switch1Valid":false,"switch2Id":1,"switch2Valid":false,"variableId":1,"variableValid":false,"variableValue":0},"directionFix":false,"image":{"characterIndex":0,"characterName":"","direction":2,"pattern":0,"tileId":0},"list":[{"code":231,"indent":0,"parameters":[41,"Dark_B",0,0,0,0,100,100,0,0]},{"code":102,"indent":0,"parameters":[["測試地圖","從起始劇情開始","從A區開始","從B區開始","從C區開始","從D區開始"],-1,0,2,0]},{"code":402,"indent":0,"parameters":[0,"測試地圖"]},{"code":117,"indent":1,"parameters":[1]},{"code":221,"indent":1,"parameters":[]},{"code":201,"indent":1,"parameters":[0,1,24,31,2,2]},{"code":211,"indent":1,"parameters":[1]},{"code":326,"indent":1,"parameters":[0,1,0,0,100]},{"code":326,"indent":1,"parameters":[0,2,0,0,100]},{"code":0,"indent":1,"parameters":[]},{"code":402,"indent":0,"parameters":[1,"從起始劇情開始"]},{"code":117,"indent":1,"parameters":[1]},{"code":221,"indent":1,"parameters":[]},{"code":201,"indent":1,"parameters":[0,6,26,7,2,2]},{"code":211,"indent":1,"parameters":[1]},{"code":117,"indent":1,"parameters":[18]},{"code":0,"indent":1,"parameters":[]},{"code":402,"indent":0,"parameters":[2,"從A區開始"]},{"code":117,"indent":1,"parameters":[1]},{"code":221,"indent":1,"parameters":[]},{"code":201,"indent":1,"parameters":[0,13,8,8,8,2]},{"code":211,"indent":1,"parameters":[1]},{"code":126,"indent":1,"parameters":[11,0,0,1]},{"code":126,"indent":1,"parameters":[51,0,0,1]},{"code":126,"indent":1,"parameters":[52,0,0,1]},{"code":126,"indent":1,"parameters":[53,0,0,1]},{"code":326,"indent":1,"parameters":[0,1,0,0,100]},{"code":121,"indent":1,"parameters":[81,86,0]},{"code":121,"indent":1,"parameters":[90,90,0]},{"code":122,"indent":1,"parameters":[11,11,0,0,1000]},{"code":122,"indent":1,"parameters":[141,141,0,0,5]},{"code":122,"indent":1,"parameters":[409,409,0,0,1]},{"code":122,"indent":1,"parameters":[420,420,0,0,1]},{"code":241,"indent":1,"parameters":[{"name":"BGM2","volume":90,"pitch":100,"pan":0}]},{"code":117,"indent":1,"parameters":[18]},{"code":222,"indent":1,"parameters":[]},{"code":117,"indent":1,"parameters":[2]},{"code":0,"indent":1,"parameters":[]},{"code":402,"indent":0,"parameters":[3,"從B區開始"]},{"code":117,"indent":1,"parameters":[1]},{"code":221,"indent":1,"parameters":[]},{"code":201,"indent":1,"parameters":[0,21,8,8,6,2]},{"code":211,"indent":1,"parameters":[1]},{"code":126,"indent":1,"parameters":[11,0,0,1]},{"code":126,"indent":1,"parameters":[51,0,0,1]},{"code":126,"indent":1,"parameters":[52,0,0,1]},{"code":126,"indent":1,"parameters":[53,0,0,1]},{"code":326,"indent":1,"parameters":[0,1,0,0,100]},{"code":121,"indent":1,"parameters":[4,6,0]},{"code":121,"indent":1,"parameters":[81,86,0]},{"code":121,"indent":1,"parameters":[90,93,0]},{"code":122,"indent":1,"parameters":[11,11,0,0,1000]},{"code":122,"indent":1,"parameters":[141,141,0,0,5]},{"code":122,"indent":1,"parameters":[409,409,0,0,1]},{"code":122,"indent":1,"parameters":[420,420,0,0,13]},{"code":122,"indent":1,"parameters":[422,422,0,0,1]},{"code":241,"indent":1,"parameters":[{"name":"BGM3","volume":90,"pitch":100,"pan":0}]},{"code":117,"indent":1,"parameters":[18]},{"code":222,"indent":1,"parameters":[]},{"code":117,"indent":1,"parameters":[2]},{"code":0,"indent":1,"parameters":[]},{"code":402,"indent":0,"parameters":[4,"從C區開始"]},{"code":117,"indent":1,"parameters":[1]},{"code":221,"indent":1,"parameters":[]},{"code":201,"indent":1,"parameters":[0,31,18,13,2,2]},{"code":211,"indent":1,"parameters":[1]},{"code":126,"indent":1,"parameters":[1,0,0,3]},{"code":126,"indent":1,"parameters":[11,0,0,1]},{"code":126,"indent":1,"parameters":[301,0,0,8]},{"code":128,"indent":1,"parameters":[1,0,0,1,false]},{"code":128,"indent":1,"parameters":[6,0,0,1,false]},{"code":126,"indent":1,"parameters":[51,0,0,1]},{"code":126,"indent":1,"parameters":[52,0,0,1]},{"code":126,"indent":1,"parameters":[53,0,0,1]},{"code":126,"indent":1,"parameters":[54,0,0,1]},{"code":126,"indent":1,"parameters":[55,0,0,1]},{"code":126,"indent":1,"parameters":[56,0,0,1]},{"code":326,"indent":1,"parameters":[0,1,0,0,100]},{"code":319,"indent":1,"parameters":[1,2,1]},{"code":319,"indent":1,"parameters":[1,3,6]},{"code":121,"indent":1,"parameters":[4,5,0]},{"code":121,"indent":1,"parameters":[8,8,0]},{"code":121,"indent":1,"parameters":[11,20,0]},{"code":121,"indent":1,"parameters":[39,39,0]},{"code":121,"indent":1,"parameters":[81,86,0]},{"code":121,"indent":1,"parameters":[90,93,0]},{"code":121,"indent":1,"parameters":[96,99,0]},{"code":122,"indent":1,"parameters":[11,11,0,0,1000]},{"code":122,"indent":1,"parameters":[127,127,0,0,7200]},{"code":122,"indent":1,"parameters":[141,141,0,0,5]},{"code":122,"indent":1,"parameters":[409,409,0,0,1]},{"code":122,"indent":1,"parameters":[420,420,0,0,13]},{"code":122,"indent":1,"parameters":[422,422,0,0,45]},{"code":122,"indent":1,"parameters":[425,425,0,0,7]},{"code":241,"indent":1,"parameters":[{"name":"BGM5","volume":90,"pitch":100,"pan":0}]},{"code":117,"indent":1,"parameters":[18]},{"code":222,"indent":1,"parameters":[]},{"code":117,"indent":1,"parameters":[2]},{"code":0,"indent":1,"parameters":[]},{"code":402,"indent":0,"parameters":[5,"從D區開始"]},{"code":117,"indent":1,"parameters":[1]},{"code":221,"indent":1,"parameters":[]},{"code":201,"indent":1,"parameters":[0,32,14,11,2,2]},{"code":211,"indent":1,"parameters":[1]},{"code":126,"indent":1,"parameters":[1,0,0,6]},{"code":126,"indent":1,"parameters":[11,0,0,3]},{"code":126,"indent":1,"parameters":[12,0,0,4]},{"code":126,"indent":1,"parameters":[21,0,0,2]},{"code":126,"indent":1,"parameters":[22,0,0,4]},{"code":126,"indent":1,"parameters":[301,0,0,14]},{"code":126,"indent":1,"parameters":[307,0,0,2]},{"code":128,"indent":1,"parameters":[1,0,0,1,false]},{"code":128,"indent":1,"parameters":[6,0,0,1,false]},{"code":128,"indent":1,"parameters":[7,0,0,1,false]},{"code":126,"indent":1,"parameters":[51,0,0,1]},{"code":126,"indent":1,"parameters":[52,0,0,1]},{"code":126,"indent":1,"parameters":[53,0,0,1]},{"code":126,"indent":1,"parameters":[54,0,0,1]},{"code":126,"indent":1,"parameters":[55,0,0,1]},{"code":126,"indent":1,"parameters":[56,0,0,1]},{"code":326,"indent":1,"parameters":[0,1,0,0,100]},{"code":319,"indent":1,"parameters":[1,2,1]},{"code":319,"indent":1,"parameters":[1,3,6]},{"code":319,"indent":1,"parameters":[1,4,7]},{"code":129,"indent":1,"parameters":[2,0,false]},{"code":326,"indent":1,"parameters":[0,2,0,0,100]},{"code":216,"indent":1,"parameters":[1]},{"code":121,"indent":1,"parameters":[4,5,0]},{"code":121,"indent":1,"parameters":[8,8,0]},{"code":121,"indent":1,"parameters":[11,20,0]},{"code":121,"indent":1,"parameters":[27,27,0]},{"code":121,"indent":1,"parameters":[39,39,0]},{"code":121,"indent":1,"parameters":[77,77,0]},{"code":121,"indent":1,"parameters":[81,86,0]},{"code":121,"indent":1,"parameters":[90,93,0]},{"code":121,"indent":1,"parameters":[96,99,0]},{"code":121,"indent":1,"parameters":[171,172,0]},{"code":121,"indent":1,"parameters":[182,184,0]},{"code":121,"indent":1,"parameters":[208,208,0]},{"code":122,"indent":1,"parameters":[11,11,0,0,1000]},{"code":122,"indent":1,"parameters":[127,127,0,0,7200]},{"code":122,"indent":1,"parameters":[141,141,0,0,5]},{"code":122,"indent":1,"parameters":[142,142,0,0,2]},{"code":122,"indent":1,"parameters":[409,409,0,0,1]},{"code":122,"indent":1,"parameters":[420,420,0,0,13]},{"code":122,"indent":1,"parameters":[422,422,0,0,45]},{"code":122,"indent":1,"parameters":[425,425,0,0,7]},{"code":122,"indent":1,"parameters":[426,426,0,0,8]},{"code":122,"indent":1,"parameters":[501,504,0,0,3]},{"code":241,"indent":1,"parameters":[{"name":"BGM5","volume":90,"pitch":100,"pan":0}]},{"code":117,"indent":1,"parameters":[18]},{"code":222,"indent":1,"parameters":[]},{"code":117,"indent":1,"parameters":[2]},{"code":0,"indent":1,"parameters":[]},{"code":404,"indent":0,"parameters":[]},{"code":0,"indent":0,"parameters":[]}],"moveFrequency":3,"moveRoute":{"list":[{"code":0,"parameters":[]}],"repeat":true,"skippable":false,"wait":false},"moveSpeed":3,"moveType":0,"priorityType":0,"stepAnime":false,"through":false,"trigger":3,"walkAnime":true}],"x":2,"y":0},
null,
null
]
}